nonebot_plugin_terralink/__init__.py
nonebot_plugin_terralink/config.py
nonebot_plugin_terralink/core/__init__.py
nonebot_plugin_terralink/core/connection.py
nonebot_plugin_terralink/core/models.py
nonebot_plugin_terralink/core/server.py
nonebot_plugin_terralink/matchers/__init__.py
nonebot_plugin_terralink/matchers/admin.py
nonebot_plugin_terralink/matchers/chat.py
nonebot_plugin_terralink/matchers/query.py
nonebot_plugin_terralink/services/__init__.py
nonebot_plugin_terralink/services/bridge.py
nonebot_plugin_terralink/services/renderer.py
nonebot_plugin_terralink-0.4.4.dist-info/METADATA
nonebot_plugin_terralink-0.4.4.dist-info/WHEEL
nonebot_plugin_terralink-0.4.4.dist-info/top_level.txt
nonebot_plugin_terralink-0.4.4.dist-info/RECORD
