Metadata-Version: 2.4
Name: nonebot-plugin-terralink
Version: 0.4.4
Summary: 实现泰拉瑞亚 TModLoader 服务器与 QQ 群双向互通的 NoneBot2 插件
Author-email: newcovid <280310454@qq.com>
License: GPL-3.0
Project-URL: Homepage, https://github.com/newcovid/nonebot-plugin-terralink
Project-URL: Documentation, https://github.com/newcovid/nonebot-plugin-terralink#readme
Keywords: nonebot,terraria,tmodloader,bridge,server,websocket
Requires-Python: >=3.9
Requires-Dist: nonebot2>=2.3.0
Requires-Dist: nonebot-adapter-onebot>=2.3.0
Requires-Dist: websockets>=11.0
Requires-Dist: pydantic>=2.0.0
Requires-Dist: nonebot-plugin-htmlrender>=0.4.0
